README.md
setup.py
pytba_calendar/__init__.py
pytba_calendar/config.py
pytba_calendar.egg-info/PKG-INFO
pytba_calendar.egg-info/SOURCES.txt
pytba_calendar.egg-info/dependency_links.txt
pytba_calendar.egg-info/requires.txt
pytba_calendar.egg-info/top_level.txt