Metadata-Version: 2.1
Name: pytba-calendar
Version: 0.1.0
Summary: InlineKeyboardButtons-Calendar for PyTelegramBotApi
Home-page: https://github.com/kazusman/pytba-calendar
Author: Pavel Anokhin
Author-email: p.a.anokhin@gmail.com
License: MIT
Keywords: telegram bot api calendar inline
Platform: UNKNOWN
